initpylib/__init__.py
initpylib/__main__.py
initpylib/templates_capi/.gitmodules
initpylib/templates_capi/CMakeLists.txt
initpylib/templates_capi/MANIFEST.in
initpylib/templates_capi/README.md
initpylib/templates_capi/setup.cfg
initpylib/templates_capi/setup.py
initpylib/templates_capi/.github/workflows/pypi.yml
initpylib/templates_capi/.github/workflows/testpypi.yml
initpylib/templates_capi/_PLEASE_PYPROJECT_NAME_/_PLEASE_PYPROJECT_NAME_.hpp
initpylib/templates_capi/_PLEASE_PYPROJECT_NAME_/__PLEASE_PYPROJECT_NAME_.cxx
initpylib/templates_capi/_PLEASE_PYPROJECT_NAME_/__init__.py
initpylib/templates_capi/_PLEASE_PYPROJECT_NAME_/main.cpp
initpylib/templates_capi/cmake/.git
initpylib/templates_capi/cmake/CPM.cmake
initpylib/templates_capi/cmake/LICENSE
initpylib/templates_capi/cmake/get_cpm.cmake
initpylib/templates_capi/cmake/pydebug.cmake
initpylib/templates_capi/cmake/testing.cmake
initpylib/templates_capi/cmake/example/core/HISTORY.md
initpylib/templates_capi/cmake/example/core/INSTALL.md
initpylib/templates_capi/cmake/example/core/LICENSE
initpylib/templates_capi/cmake/example/core/README.md
initpylib/templates_capi/cmake/example/core/header-only/application/CMakeLists.txt
initpylib/templates_capi/cmake/example/core/header-only/application/build.bat
initpylib/templates_capi/cmake/example/core/header-only/application/build.sh
initpylib/templates_capi/cmake/example/core/header-only/application/configure.bat
initpylib/templates_capi/cmake/example/core/header-only/application/configure.sh
initpylib/templates_capi/cmake/example/core/header-only/application/main.cpp
initpylib/templates_capi/cmake/example/core/header-only/library/CMakeLists.txt
initpylib/templates_capi/cmake/example/core/header-only/library/configure.bat
initpylib/templates_capi/cmake/example/core/header-only/library/configure.sh
initpylib/templates_capi/cmake/example/core/header-only/library/install.bat
initpylib/templates_capi/cmake/example/core/header-only/library/install.sh
initpylib-0.4.3.dist-info/LICENSE
initpylib-0.4.3.dist-info/METADATA
initpylib-0.4.3.dist-info/WHEEL
initpylib-0.4.3.dist-info/entry_points.txt
initpylib-0.4.3.dist-info/top_level.txt
initpylib-0.4.3.dist-info/RECORD
