Metadata-Version: 2.1
Name: initpylib
Version: 0.4.3
Summary: Build Python Project Skelton
Home-page: https://github.com/kirin123kirin/initpylib.git
Author: kirin123kirin
License: MIT
Keywords: template,skelton,CAPI,ExtendModule
Platform: UNKNOWN
Classifier: Programming Language :: Python :: 3
Classifier: Programming Language :: Python :: 3.6
Classifier: Programming Language :: Python :: 3.7
Classifier: Programming Language :: Python :: 3.8
Classifier: Programming Language :: Python :: 3.9
Classifier: Programming Language :: Python :: 3.10
Classifier: License :: OSI Approved :: MIT License
License-File: LICENSE
Requires-Dist: setuptools (>=42)
Requires-Dist: wheel
